custom_card_component/__init__.py
custom_card_component/frontend/build/asset-manifest.json
custom_card_component/frontend/build/bootstrap.min.css
custom_card_component/frontend/build/index.html
custom_card_component/frontend/build/precache-manifest.548d3303618cc8d0addf9c660f5248be.js
custom_card_component/frontend/build/service-worker.js
custom_card_component/frontend/build/static/js/2.69e5eb1f.chunk.js
custom_card_component/frontend/build/static/js/2.69e5eb1f.chunk.js.LICENSE.txt
custom_card_component/frontend/build/static/js/2.69e5eb1f.chunk.js.map
custom_card_component/frontend/build/static/js/main.ed718770.chunk.js
custom_card_component/frontend/build/static/js/main.ed718770.chunk.js.map
custom_card_component/frontend/build/static/js/runtime-main.44d30fc2.js
custom_card_component/frontend/build/static/js/runtime-main.44d30fc2.js.map
custom_card_component-0.0.1.dist-info/LICENSE
custom_card_component-0.0.1.dist-info/METADATA
custom_card_component-0.0.1.dist-info/WHEEL
custom_card_component-0.0.1.dist-info/top_level.txt
custom_card_component-0.0.1.dist-info/RECORD
